cosmoboost/__init__.py
cosmoboost/blueprints.py
cosmoboost/cosmoboost.py
cosmoboost/lib/FileHandler.py
cosmoboost/lib/FrequencyFunctions.py
cosmoboost/lib/KernelODE.py
cosmoboost/lib/KernelRecursive.py
cosmoboost/lib/MatrixHandler.py
cosmoboost/lib/__init__.py
cosmoboost/lib/jeong.py
cosmoboost/lib/mytimer.py
cosmoboost/lib/sample_Cl.npz
cosmoboost-1.1.6.data/data/sample_Cl.npz
cosmoboost-1.1.6.dist-info/LICENSE
cosmoboost-1.1.6.dist-info/METADATA
cosmoboost-1.1.6.dist-info/WHEEL
cosmoboost-1.1.6.dist-info/top_level.txt
cosmoboost-1.1.6.dist-info/RECORD
