Metadata-Version: 2.1
Name: cosmoboost
Version: 1.1.6
Summary: a python package for boosting the cosmos!
Home-page: https://github.com/syasini/CosmoBoost
Author: Siavash Yasini
Author-email: yasini@usc.edu
License: MIT
Platform: UNKNOWN
Requires-Dist: matplotlib (>=3.1.2)
Requires-Dist: numpy (>=1.17.3)
Requires-Dist: pytest (>=5.3.1)
Requires-Dist: scipy (>=1.3.0)
Requires-Dist: healpy (>=1.12.9)
Requires-Dist: tqdm (>=4.38.0)
